instaui_mermaid/__init__.py
instaui_mermaid/_mermaid.py
instaui_mermaid/static/instaui-mermaid.js
instaui_mermaid/static/mermaid.esm.min.mjs
instaui_mermaid/static/chunks/mermaid.esm.min/architecture-U656AL7Q-3ZQKGQJL.mjs
instaui_mermaid/static/chunks/mermaid.esm.min/architectureDiagram-4X3Z3J56.mjs
instaui_mermaid/static/chunks/mermaid.esm.min/blockDiagram-MFEFEJY7.mjs
instaui_mermaid/static/chunks/mermaid.esm.min/c4Diagram-Q5SP5FFD.mjs
instaui_mermaid/static/chunks/mermaid.esm.min/chunk-2XYWPRAO.mjs
instaui_mermaid/static/chunks/mermaid.esm.min/chunk-353K7GK5.mjs
instaui_mermaid/static/chunks/mermaid.esm.min/chunk-4KE642ED.mjs
instaui_mermaid/static/chunks/mermaid.esm.min/chunk-5V7UUW6L.mjs
instaui_mermaid/static/chunks/mermaid.esm.min/chunk-63GW7ZVL.mjs
instaui_mermaid/static/chunks/mermaid.esm.min/chunk-6DHVG6KC.mjs
instaui_mermaid/static/chunks/mermaid.esm.min/chunk-6EQESGSB.mjs
instaui_mermaid/static/chunks/mermaid.esm.min/chunk-6XQQT3RD.mjs
instaui_mermaid/static/chunks/mermaid.esm.min/chunk-7SRKK4IT.mjs
instaui_mermaid/static/chunks/mermaid.esm.min/chunk-A4ITRWGT.mjs
instaui_mermaid/static/chunks/mermaid.esm.min/chunk-A6NU47M6.mjs
instaui_mermaid/static/chunks/mermaid.esm.min/chunk-ASAHGCDZ.mjs
instaui_mermaid/static/chunks/mermaid.esm.min/chunk-BHQAJ5QI.mjs
instaui_mermaid/static/chunks/mermaid.esm.min/chunk-DY3L2I7V.mjs
instaui_mermaid/static/chunks/mermaid.esm.min/chunk-EFRVIJHI.mjs
instaui_mermaid/static/chunks/mermaid.esm.min/chunk-EOITJJC2.mjs
instaui_mermaid/static/chunks/mermaid.esm.min/chunk-EQI6KKA3.mjs
instaui_mermaid/static/chunks/mermaid.esm.min/chunk-F3RBCZRS.mjs
instaui_mermaid/static/chunks/mermaid.esm.min/chunk-GOL2OBWC.mjs
instaui_mermaid/static/chunks/mermaid.esm.min/chunk-GTKDMUJJ.mjs
instaui_mermaid/static/chunks/mermaid.esm.min/chunk-IQQE2MEC.mjs
instaui_mermaid/static/chunks/mermaid.esm.min/chunk-JXEFGRG2.mjs
instaui_mermaid/static/chunks/mermaid.esm.min/chunk-KXVH62NG.mjs
instaui_mermaid-0.2.0.dist-info/METADATA
instaui_mermaid-0.2.0.dist-info/WHEEL
instaui_mermaid-0.2.0.dist-info/licenses/LICENSE
instaui_mermaid-0.2.0.dist-info/RECORD
