Metadata-Version: 2.4
Name: instaui-mermaid
Version: 0.2.0
Summary: A Python package for generating mermaid diagrams in InstaUI.
Author-email: CrystalWindSnake <568166495@qq.com>
License-Expression: MIT
License-File: LICENSE
Keywords: gui,instaui,mermaid,ui,web
Requires-Python: <3.14,>=3.10
Requires-Dist: instaui>=0.8.5
